MANIFEST.in
README.md
requirements.txt
setup.py
aiconfig/__init__.py
aiconfig/__main__.py
aiconfig/builder.py
aiconfig/version.py
aiconfig.egg-info/PKG-INFO
aiconfig.egg-info/SOURCES.txt
aiconfig.egg-info/dependency_links.txt
aiconfig.egg-info/entry_points.txt
aiconfig.egg-info/requires.txt
aiconfig.egg-info/top_level.txt