Metadata-Version: 2.1
Name: aiconfig
Version: 0.0.1.dev5
Summary: AI task configuration  with YAML.
Home-page: https://github.com/lf1-io/aiconfig
Author: LF1
Author-email: contact@lf1.io
License: Apache 2.0
Platform: UNKNOWN
Classifier: Programming Language :: Python :: 3.6
Classifier: Programming Language :: Python :: 3.7
Classifier: Programming Language :: Python :: 3.8
Classifier: Programming Language :: Python :: 3.9
Classifier: Topic :: Scientific/Engineering
Classifier: Topic :: Scientific/Engineering :: Artificial Intelligence
Requires-Python: >=3.6
